plaque/__init__.py
plaque/api_formatter.py
plaque/ast_parser.py
plaque/cell.py
plaque/cli.py
plaque/dependency_analyzer.py
plaque/display.py
plaque/environment.py
plaque/formatter.py
plaque/iowrapper.py
plaque/processor.py
plaque/renderables.py
plaque/server.py
plaque/watcher.py
plaque/templates/notebook.html
plaque-0.4.0.dist-info/METADATA
plaque-0.4.0.dist-info/WHEEL
plaque-0.4.0.dist-info/entry_points.txt
plaque-0.4.0.dist-info/licenses/LICENSE
plaque-0.4.0.dist-info/RECORD
