Metadata-Version: 2.4
Name: plaque
Version: 0.4.0
Summary: A local-first notebook system for Python, inspired by Clerk for Clojure
Project-URL: Homepage, https://github.com/alexalemi/plaque
Project-URL: Repository, https://github.com/alexalemi/plaque
Project-URL: Issues, https://github.com/alexalemi/plaque/issues
Project-URL: Documentation, https://github.com/alexalemi/plaque#readme
Author-email: Alex Alemi <alexalemi@gmail.com>
License: MIT
License-File: LICENSE
Keywords: clerk,interactive,jupyter,local-first,markdown,notebook,python
Classifier: Development Status :: 4 - Beta
Classifier: Intended Audience :: Developers
Classifier: Intended Audience :: Science/Research
Classifier: License :: OSI Approved :: MIT License
Classifier: Operating System :: OS Independent
Classifier: Programming Language :: Python :: 3
Classifier: Programming Language :: Python :: 3.13
Classifier: Topic :: Scientific/Engineering
Classifier: Topic :: Software Development :: Libraries :: Python Modules
Classifier: Topic :: Text Processing :: Markup :: Markdown
Requires-Python: >=3.11
Requires-Dist: click>=8.0.0
Requires-Dist: ipython>=8.0.0
Requires-Dist: markdown>=3.0.0
Requires-Dist: pygments>=2.0.0
Requires-Dist: watchdog>=6.0.0
